{"coord":{"lon":52.4289,"lat":55.7561},"weather":[{"id":804,"main":"Clouds","description":"\u043f\u0430\u0441\u043c\u0443\u0440\u043d\u043e","icon":"04d"}],"base":"stations","main":{"temp":8.49,"feels_like":7.48,"temp_min":8.49,"temp_max":8.49,"pressure":1021,"humidity":54,"sea_level":1021,"grnd_level":1007},"visibility":10000,"wind":{"speed":1.95,"deg":157,"gust":2.64},"clouds":{"all":100},"dt":1760517229,"sys":{"type":1,"id":9039,"country":"RU","sunrise":1760497241,"sunset":1760535068},"timezone":10800,"id":523750,"name":"\u041d\u0430\u0431\u0435\u0440\u0435\u0436\u043d\u044b\u0435 \u0427\u0435\u043b\u043d\u044b","cod":200,"city_name":"Naberezhnye Chelny","last_update":1760517349}